kumori/__init__.py
kumori/qcloud/__init__.py
kumori/qcloud/core.py
kumori/qcloud/errors.py
kumori/qcloud/sig_v1.py
kumori-0.0.4.dist-info/licenses/LICENSE
kumori-0.0.4.dist-info/METADATA
kumori-0.0.4.dist-info/WHEEL
kumori-0.0.4.dist-info/top_level.txt
kumori-0.0.4.dist-info/RECORD
