Metadata-Version: 2.4
Name: kumori
Version: 0.0.4
Summary: Calling Tencent Cloud API in a easier way
Author-email: kayoch1n <hanayolawk@gmail.com>
License-Expression: GPL-3.0-only
Project-URL: Homepage, https://github.com/kayoch1n/kumori
Project-URL: Issues, https://github.com/kayoch1n/kumori/issues
Classifier: Programming Language :: Python :: 3
License-File: LICENSE
Requires-Dist: requests
Dynamic: license-file
